uc_browser/__init__.py
uc_browser/browser.py
uc_browser/infra/__init__.py
uc_browser/infra/undetected_webdriver.py
uc_browser/infra/utils.py
uc_browser/undetected_chromedriver/__init__.py
uc_browser/undetected_chromedriver/cdp.py
uc_browser/undetected_chromedriver/devtool.py
uc_browser/undetected_chromedriver/dprocess.py
uc_browser/undetected_chromedriver/options.py
uc_browser/undetected_chromedriver/patcher.py
uc_browser/undetected_chromedriver/reactor.py
uc_browser/undetected_chromedriver/webelement.py
uc_browser-0.4.3.dist-info/METADATA
uc_browser-0.4.3.dist-info/WHEEL
uc_browser-0.4.3.dist-info/RECORD
